Metadata-Version: 2.1
Name: datasette-render-image-tags
Version: 0.1
Summary: Turn any URLs ending in .jpg/.png/.gif into img tags with width 200
Home-page: https://github.com/simonw/datasette-render-image-tags
Author: Simon Willison
License: Apache License, Version 2.0
Project-URL: Issues, https://github.com/simonw/datasette-render-image-tags/issues
Project-URL: CI, https://github.com/simonw/datasette-render-image-tags/actions
Project-URL: Changelog, https://github.com/simonw/datasette-render-image-tags/releases
Classifier: Framework :: Datasette
Classifier: License :: OSI Approved :: Apache Software License
Requires-Python: >=3.7
License-File: LICENSE
Requires-Dist: datasette
Provides-Extra: test
Requires-Dist: pytest ; extra == 'test'
Requires-Dist: pytest-asyncio ; extra == 'test'
